pycmdstan/__init__.py
pycmdstan/__main__.py
pycmdstan/io.py
pycmdstan/model.py
pycmdstan/psis.py
pycmdstan/tests.py
pycmdstan/viz.py
pycmdstan-0.9.dist-info/METADATA
pycmdstan-0.9.dist-info/RECORD
pycmdstan-0.9.dist-info/WHEEL
pycmdstan-0.9.dist-info/top_level.txt
