Metadata-Version: 2.1
Name: pycmdstan
Version: 0.9
Summary: Python interface to CmdStan
Home-page: https://gitlab.thevirtualbrain.org/tvb/pycmdstan
Author: Marmaduke Woodman
Author-email: marmaduke.woodman@univ-amu.fr
License: UNKNOWN
Platform: UNKNOWN
Classifier: Programming Language :: Python :: 3
Classifier: License :: OSI Approved :: Apache Software License
Classifier: Operating System :: OS Independent
Classifier: Development Status :: 4 - Beta
Classifier: Intended Audience :: Science/Research
Classifier: Natural Language :: English
Classifier: Programming Language :: Other
Classifier: Programming Language :: C++
Classifier: Topic :: Scientific/Engineering :: Information Analysis
Requires-Dist: numpy
Requires-Dist: filelock
Requires-Dist: matplotlib
